MANIFEST.in
README.md
requirements.txt
setup.py
abt/__init__.py
abt/format.py
abt/rpc_client.py
abt/torrent.py
abt/transport.py
abt.egg-info/PKG-INFO
abt.egg-info/SOURCES.txt
abt.egg-info/dependency_links.txt
abt.egg-info/entry_points.txt
abt.egg-info/requires.txt
abt.egg-info/top_level.txt