Metadata-Version: 1.0
Name: abt
Version: 0.1.0
Summary: BitTorrent workflow with aria2.
Home-page: https://github.com/kamikat/abt
Author: Kamikat
Author-email: kamikat@banana.moe
License: MIT
Platform: UNKNOWN
